architect_py/__init__.py
architect_py/async_client.py
architect_py/async_cpty.py
architect_py/batch_place_order.py
architect_py/client.py
architect_py/client.pyi
architect_py/common_types/__init__.py
architect_py/common_types/order_dir.py
architect_py/common_types/time_in_force.py
architect_py/common_types/tradable_product.py
architect_py/graphql_client/__init__.py
architect_py/graphql_client/base_model.py
architect_py/graphql_client/client.py
architect_py/graphql_client/enums.py
architect_py/graphql_client/exceptions.py
architect_py/graphql_client/fragments.py
architect_py/graphql_client/get_execution_info_query.py
architect_py/graphql_client/get_execution_infos_query.py
architect_py/graphql_client/get_first_notice_date_query.py
architect_py/graphql_client/get_future_series_query.py
architect_py/graphql_client/get_product_info_query.py
architect_py/graphql_client/get_product_infos_query.py
architect_py/graphql_client/input_types.py
architect_py/graphql_client/juniper_base_client.py
architect_py/graphql_client/search_symbols_query.py
architect_py/graphql_client/user_id_query.py
architect_py/grpc/__init__.py
architect_py/grpc/client.py
architect_py/grpc/orderflow.py
architect_py/grpc/resolve_endpoint.py
architect_py/grpc/server.py
architect_py/grpc/utils.py
architect_py/grpc/models/__init__.py
architect_py/grpc/models/definitions.py
architect_py/grpc/models/Accounts/AccountsRequest.py
architect_py/grpc/models/Accounts/AccountsResponse.py
architect_py/grpc/models/Accounts/OpenPaperAccountRequest.py
architect_py/grpc/models/Accounts/OpenPaperAccountResponse.py
architect_py/grpc/models/Accounts/ResetPaperAccountRequest.py
architect_py/grpc/models/Accounts/ResetPaperAccountResponse.py
architect_py/grpc/models/Accounts/__init__.py
architect_py/grpc/models/Algo/AlgoOrder.py
architect_py/grpc/models/Algo/AlgoOrderRequest.py
architect_py/grpc/models/Algo/AlgoOrdersRequest.py
architect_py/grpc/models/Algo/AlgoOrdersResponse.py
architect_py-5.9.2.dist-info/licenses/LICENSE
architect_py-5.9.2.dist-info/METADATA
architect_py-5.9.2.dist-info/WHEEL
architect_py-5.9.2.dist-info/top_level.txt
architect_py-5.9.2.dist-info/RECORD
