Metadata-Version: 2.4
Name: architect-py
Version: 5.9.2
Summary: Python SDK for the Architect trading platform and brokerage.
Author-email: "Architect Financial Technologies, Inc." <hello@architect.co>
License-Expression: Apache-2.0
Project-URL: Documentation, https://docs.architect.co
Project-URL: Homepage, https://www.architect.co/brokerage/overview
Project-URL: Repository, https://github.com/architect-xyz/architect-py
Classifier: Programming Language :: Python :: 3
Classifier: Operating System :: OS Independent
Classifier: Development Status :: 5 - Production/Stable
Requires-Python: <4,>=3.10
License-File: LICENSE
Requires-Dist: asyncio>=3
Requires-Dist: dnspython>=2.0
Requires-Dist: gql[httpx]<4,>=3.5.0
Requires-Dist: grpcio>=1.66.1
Requires-Dist: msgspec<0.20,>=0.19
Requires-Dist: pandas>=2
Requires-Dist: pydantic~=2.10
Dynamic: license-file
